{"sections":{"main":{"type":"main-blog-post","blocks":{"newsletter":{"type":"newsletter","settings":{"title":"Get Fit with Elite Fitness!","content":"<p>Sign up now to receive regular updates and take your fitness journey to the next level with Elite Fitness.<\/p>","subtext":"100% free, Unsubscribe any time!","background":"#1e2d7d","text":"#ffffff"}},"social-media":{"type":"social_media","settings":{"title":"Follow us","show_rss":true}}},"block_order":["newsletter","social-media"],"settings":{"show_category":true,"show_author":true,"show_date":true,"show_share_buttons":true,"show_tags":true,"show_gravatar":true}}},"order":["main"]}